<annotation>
	<folder>non_annotated</folder>
	<filename>580x580 - 2020-12-05T165219.246.jpg</filename>
	<path>D:\Projects\WineNot\LabelExtractorTensorflow\Dataset\non_annotated\580x580 - 2020-12-05T165219.246.jpg</path>
	<source>
		<database>Unknown</database>
	</source>
	<size>
		<width>180</width>
		<height>180</height>
		<depth>3</depth>
	</size>
	<segmented>0</segmented>
	<object>
		<name>label</name>
		<pose>Unspecified</pose>
		<truncated>0</truncated>
		<difficult>0</difficult>
		<bndbox>
			<xmin>66</xmin>
			<ymin>82</ymin>
			<xmax>115</xmax>
			<ymax>145</ymax>
		</bndbox>
	</object>
</annotation>
